pytigon
